setup.py
pytinder.egg-info/PKG-INFO
pytinder.egg-info/SOURCES.txt
pytinder.egg-info/dependency_links.txt
pytinder.egg-info/requires.txt
pytinder.egg-info/top_level.txt
tinder/__init__.py
tinder/api.py
tinder/binder.py
tinder/constants.py
tinder/exceptions.py
tinder/models.py
tinder/utils.py