Metadata-Version: 1.1
Name: pytinder
Version: 0.1b0
Summary: Python Interface for the Tinder API
Home-page: https://bitbucket.org/netlandish/pytinder/
Author: Netlandish Inc.
Author-email: hello@netlandish.com
License: UNKNOWN
Platform: any
Classifier: Development Status :: 4 - Beta
Classifier: Intended Audience :: Developers
Classifier: Natural Language :: English
Classifier: Operating System :: OS Independent
Classifier: Programming Language :: Python
Classifier: Programming Language :: Python :: 2.6
Classifier: Programming Language :: Python :: 2.7
Classifier: Environment :: Web Environment
